exclude_until_coverage_plugin/__init__.py
exclude_until_coverage_plugin/exclude_until.py
exclude_until_coverage_plugin-0.3.0.dist-info/LICENSE
exclude_until_coverage_plugin-0.3.0.dist-info/METADATA
exclude_until_coverage_plugin-0.3.0.dist-info/WHEEL
exclude_until_coverage_plugin-0.3.0.dist-info/top_level.txt
exclude_until_coverage_plugin-0.3.0.dist-info/RECORD
